{
  "name": "NotePersona",
  "fields": [
    {
      "fieldName": "idPersonaRef",
      "fieldType": "Long",
      "fieldValidateRules": ["required"]
    },
    {
      "fieldName": "testo",
      "fieldType": "String"
    }
  ],
  "relationships": [
    {
      "relationshipType": "many-to-one",
      "otherEntityName": "persona",
      "otherEntityRelationshipName": "notePersona",
      "relationshipName": "idPersonaRef",
      "otherEntityField": "id"
    }
  ],
  "changelogDate": "20200617084828",
  "entityTableName": "note_persona",
  "dto": "mapstruct",
  "pagination": "no",
  "service": "serviceClass",
  "jpaMetamodelFiltering": false,
  "fluentMethods": true,
  "readOnly": false,
  "embedded": false,
  "clientRootFolder": "",
  "applications": ["eoloprj"]
}
